superFunc/__init__.py
superFunc/func.py
superFunc-2.9.0.dist-info/METADATA
superFunc-2.9.0.dist-info/WHEEL
superFunc-2.9.0.dist-info/top_level.txt
superFunc-2.9.0.dist-info/RECORD
