Metadata-Version: 2.1
Name: superFunc
Version: 2.9.0
Summary: Bu harika bir Python kütüphanesi örneğidir. Yorumlarinizi lutfen bizimle paylasiniz.
Home-page: https://github.com/hocuf
Author: Abdullah Fatih Hocu
Author-email: hocuaf@gmail.com
License: UNKNOWN
Keywords: ornek kutuphane python
Platform: UNKNOWN
